segmind_workflow/__init__.py
segmind_workflow/models_data.json
segmind_workflow/slug_data.json
segmind_workflow/temp.png
segmind_workflow/testing.ipynb
segmind_workflow/workflow.py
segmind_workflow/__pycache__/workflow.cpython-311.pyc
segmind_workflow/__pycache__/workflow.cpython-312.pyc
segmind_workflow-0.1.13.dist-info/LICENSE
segmind_workflow-0.1.13.dist-info/METADATA
segmind_workflow-0.1.13.dist-info/WHEEL
segmind_workflow-0.1.13.dist-info/top_level.txt
segmind_workflow-0.1.13.dist-info/RECORD
