Metadata-Version: 2.1
Name: segmind-workflow
Version: 0.1.13
Summary: A package for managing workflows with various functions.
Author: Srujan
Author-email: nagamallisrujan@gmail.com
License: MIT
Classifier: Programming Language :: Python :: 3
Classifier: License :: OSI Approved :: MIT License
Classifier: Operating System :: OS Independent
Requires-Python: >=3.6
License-File: LICENSE
Requires-Dist: pillow
Requires-Dist: importlib
Requires-Dist: requests
